Doctor_Doom/Doctor_Doom.py
Doctor_Doom/__init__.py
doctor_doom-0.0.dist-info/METADATA
doctor_doom-0.0.dist-info/WHEEL
doctor_doom-0.0.dist-info/top_level.txt
doctor_doom-0.0.dist-info/RECORD
